anyloadump/__init__.py
anyloadump/dump.py
anyloadump/load.py
anyloadump/loadump.py
anyloadump-0.1.dist-info/DESCRIPTION.rst
anyloadump-0.1.dist-info/METADATA
anyloadump-0.1.dist-info/RECORD
anyloadump-0.1.dist-info/WHEEL
anyloadump-0.1.dist-info/entry_points.txt
anyloadump-0.1.dist-info/metadata.json
anyloadump-0.1.dist-info/top_level.txt
