Metadata-Version: 2.0
Name: anyloadump
Version: 0.1
Summary: dumper and loader for various file formats.
Home-page: https://github.com/knknkn1162/anyloadump
Author: knknkn1162
Author-email: knknkn1162@gmail.com
License: MIT
Platform: UNKNOWN
Classifier: Programming Language :: Python :: 3.5
Classifier: Programming Language :: Python :: 3.6
